tensorflow/__init__.py
tensorflow/api_template.__init__.py
tensorflow/api_template_v1.__init__.py
tensorflow/compat_template.__init__.py
tensorflow/compat_template_v1.__init__.py
tensorflow/virtual_root_template_v1.__init__.py
tensorflow/virtual_root_template_v2.__init__.py
tensorflow/contrib/__init__.py
tensorflow/contrib/all_reduce/__init__.py
tensorflow/contrib/autograph/__init__.py
tensorflow/contrib/batching/__init__.py
tensorflow/contrib/bayesflow/__init__.py
tensorflow/contrib/bayesflow/python/__init__.py
tensorflow/contrib/bigtable/__init__.py
tensorflow/contrib/boosted_trees/__init__.py
tensorflow/contrib/boosted_trees/estimator_batch/__init__.py
tensorflow/contrib/boosted_trees/estimator_batch/custom_export_strategy.py
tensorflow/contrib/boosted_trees/estimator_batch/custom_export_strategy_test.py
tensorflow/contrib/boosted_trees/estimator_batch/custom_loss_head.py
tensorflow/contrib/boosted_trees/estimator_batch/distillation_loss.py
tensorflow/contrib/boosted_trees/estimator_batch/dnn_tree_combined_estimator.py
tensorflow/contrib/boosted_trees/estimator_batch/dnn_tree_combined_estimator_test.py
tensorflow/contrib/boosted_trees/estimator_batch/estimator.py
tensorflow/contrib/boosted_trees/estimator_batch/estimator_test.py
tensorflow/contrib/boosted_trees/estimator_batch/estimator_utils.py
tensorflow/contrib/boosted_trees/estimator_batch/model.py
tensorflow/contrib/boosted_trees/estimator_batch/trainer_hooks.py
tensorflow/contrib/boosted_trees/estimator_batch/trainer_hooks_test.py
tensorflow/contrib/boosted_trees/python/__init__.py
tensorflow/contrib/boosted_trees/python/training/__init__.py
tensorflow/contrib/boosted_trees/python/training/functions/__init__.py
tensorflow/contrib/boosted_trees/python/training/functions/gbdt_batch.py
tensorflow/contrib/boosted_trees/python/training/functions/gbdt_batch_test.py
tensorflow/contrib/boosted_trees/python/utils/__init__.py
tensorflow/contrib/boosted_trees/python/utils/losses.py
tensorflow1_fork-1.15.2.1.dist-info/AUTHORS
tensorflow1_fork-1.15.2.1.dist-info/LICENSE
tensorflow1_fork-1.15.2.1.dist-info/METADATA
tensorflow1_fork-1.15.2.1.dist-info/WHEEL
tensorflow1_fork-1.15.2.1.dist-info/top_level.txt
tensorflow1_fork-1.15.2.1.dist-info/RECORD
