Metadata-Version: 2.1
Name: tensorflow1-fork
Version: 1.15.2.1
Summary: tensorflow_1.15.2
Author: M.Uchiyama
License: MIT
Keywords: TensorFlowFork
Classifier: License :: OSI Approved :: MIT License
Classifier: Programming Language :: Python :: 3.7
License-File: LICENSE
License-File: AUTHORS
